kashmir/__init__.py
kashmir/__main__.py
kashmir/cli.py
kashmir/core/__init__.py
kashmir/core/data.py
kashmir/core/entities/__init__.py
kashmir/core/entities/project.py
kashmir/core/protocols/__init__.py
kashmir/core/protocols/entity.py
kashmir/core/protocols/repository.py
kashmir/core/providers/__init__.py
kashmir/core/providers/scm.py
kashmir/providers/__init__.py
kashmir/providers/gitlab.py
kashmir/repositories/__init__.py
kashmir/repositories/project.py
kashmir/usecases/__init__.py
kashmir/usecases/new_fix.py
kashmir/usecases/new_release.py
kashmir-2019.2.0.dist-info/entry_points.txt
kashmir-2019.2.0.dist-info/LICENSE
kashmir-2019.2.0.dist-info/WHEEL
kashmir-2019.2.0.dist-info/METADATA
kashmir-2019.2.0.dist-info/RECORD
