Metadata-Version: 2.1
Name: kashmir
Version: 2019.2.0
Summary: Snow's DevOps CLI Toolkit
Home-page: https://gitlab.com/snowman-labs/kashmir
License: Apache-2.0
Keywords: cli,tooling,devops
Author: Johnny Wellington
Author-email: johnny.w.santos@gmail.com
Requires-Python: >=3.7,<4.0
Classifier: License :: OSI Approved :: Apache Software License
Classifier: Programming Language :: Python :: 3
Classifier: Programming Language :: Python :: 3.7
Requires-Dist: click (>=7.0,<8.0)
Requires-Dist: python-gitlab (>=1.13,<2.0)
Requires-Dist: typing-extensions (>=3.7,<4.0)
Project-URL: Repository, https://gitlab.com/snowman-labs/kashmir
